LICENSE
MANIFEST.in
README.md
setup.py
email_miner/__init__.py
email_miner/__version__.py
email_miner/email.py
email_miner/miner.py
email_miner/parse.py
email_miner.egg-info/PKG-INFO
email_miner.egg-info/SOURCES.txt
email_miner.egg-info/dependency_links.txt
email_miner.egg-info/requires.txt
email_miner.egg-info/top_level.txt