Metadata-Version: 2.1
Name: email-miner
Version: 0.0.3
Summary: Email miner makes it easy to mine IMAP mailboxes in a simple pythonic way.
Home-page: https://github.com/niranjan94/py-email-miner
Author: Niranjan Rajendran
Author-email: me@niranjan.io
License: MIT
Platform: UNKNOWN
Classifier: License :: OSI Approved :: MIT License
Classifier: Programming Language :: Python
Classifier: Programming Language :: Python :: 3
Classifier: Programming Language :: Python :: 3.6
Classifier: Programming Language :: Python :: 3.7
Classifier: Programming Language :: Python :: Implementation :: CPython
Classifier: Programming Language :: Python :: Implementation :: PyPy
Requires-Python: >=3.6.0
